datarobot_mlops/collections/__init__.py
datarobot_mlops/collections/batch_data_histogram.py
datarobot_mlops/collections/data_histogram.py
datarobot_mlops/collections/feature_list.py
datarobot_mlops/collections/lru_data_histogram.py
datarobot_mlops/collections/utils.py
datarobot_mlops/drift/__init__.py
datarobot_mlops/drift/feature_distributions.py
datarobot_mlops/drift/metrics.py
datarobot_mlops/drift/report.py
datarobot_mlops/drift/utils.py
datarobot_mlops/stats_aggregator/__init__.py
datarobot_mlops/stats_aggregator/aggregates.py
datarobot_mlops/stats_aggregator/aggregation.py
datarobot_mlops/stats_aggregator/constants.py
datarobot_mlops/stats_aggregator/histogram.py
datarobot_mlops/stats_aggregator/merging.py
datarobot_mlops/stats_aggregator/stats.py
datarobot_mlops/stats_aggregator/type_conversion.py
datarobot_mlops/stats_aggregator/types.py
datarobot_mlops/stats_aggregator/utils.py
datarobot_mlops_stats_aggregator-10.2.3.dist-info/METADATA
datarobot_mlops_stats_aggregator-10.2.3.dist-info/WHEEL
datarobot_mlops_stats_aggregator-10.2.3.dist-info/RECORD
