Metadata-Version: 2.1
Name: datarobot-mlops-stats-aggregator
Version: 10.2.3
Summary: DataRobot library to compute statistics aggregations
License: Apache-2.0
Author: DataRobot
Author-email: support@datarobot.com
Requires-Python: >=3.7.1,<3.13
Classifier: License :: OSI Approved :: Apache Software License
Classifier: Operating System :: MacOS
Classifier: Operating System :: POSIX
Classifier: Operating System :: Unix
Classifier: Programming Language :: Python :: 3
Classifier: Programming Language :: Python :: 3.8
Classifier: Programming Language :: Python :: 3.9
Classifier: Programming Language :: Python :: 3.10
Classifier: Programming Language :: Python :: 3.11
Requires-Dist: drfaster (>=9.0.0)
Requires-Dist: numpy (>=1.21.4)
Requires-Dist: pandas (>=1.3.4)
